jnumpy/__init__.py
jnumpy/core.py
jnumpy/nn.py
jnumpy/rl/__init__.py
jnumpy/rl/agents.py
jnumpy/rl/core.py
jnumpy/rl/types.py
jnumpy-1.1.dist-info/LICENSE
jnumpy-1.1.dist-info/METADATA
jnumpy-1.1.dist-info/WHEEL
jnumpy-1.1.dist-info/top_level.txt
jnumpy-1.1.dist-info/RECORD
