Metadata-Version: 2.1
Name: jnumpy
Version: 1.1
Summary: Jacob's numpy library for machine learning.
Home-page: https://github.com/JacobFV/jnumpy
Author: Jacob Valdez
Author-email: jacobfv@msn.com
License: UNKNOWN
Project-URL: Homepage, https://github.com/JacobFV/jnumpy
Keywords: numpy machine learning automatic differentiation
Platform: UNKNOWN
Classifier: Programming Language :: Python :: 3
Classifier: License :: OSI Approved :: MIT License
Classifier: Operating System :: OS Independent
Requires-Python: >=3.6
Requires-Dist: numpy
